[{"name":"Central Province","native":null,"cities":[{"name":"Tulagi","native":null,"lat":"-9.10306000","lon":"160.15056000"}]},{"name":"Choiseul Province","native":null,"cities":[]},{"name":"Guadalcanal Province","native":null,"cities":[{"name":"Honiara","native":null,"lat":"-9.43333000","lon":"159.95000000"}]},{"name":"Honiara","native":null,"cities":[]},{"name":"Isabel Province","native":null,"cities":[{"name":"Buala","native":null,"lat":"-8.14497000","lon":"159.59212000"}]},{"name":"Makira-Ulawa Province","native":null,"cities":[{"name":"Kirakira","native":null,"lat":"-10.45442000","lon":"161.92045000"}]},{"name":"Malaita Province","native":null,"cities":[{"name":"Auki","native":null,"lat":"-8.76778000","lon":"160.69778000"}]},{"name":"Rennell and Bellona Province","native":null,"cities":[]},{"name":"Temotu Province","native":null,"cities":[{"name":"Lata","native":null,"lat":"-10.72500000","lon":"165.79722000"}]},{"name":"Western Province","native":null,"cities":[{"name":"Gizo","native":null,"lat":"-8.10303000","lon":"156.84186000"}]}]