[{"id":4183,"name":"Ajdovščina Municipality","native":null,"cities":[{"id":104059,"name":"Ajdovščina","native":null,"lat":"45.88601000","lon":"13.90946000"},{"id":104084,"name":"Cirkulane","native":null,"lat":"46.34408000","lon":"15.99472000"},{"id":104174,"name":"Lokavec","native":null,"lat":"45.90167000","lon":"13.87972000"}]},{"id":4326,"name":"Ankaran Municipality","native":null,"cities":[{"id":104060,"name":"Ankaran","native":null,"lat":"45.57861000","lon":"13.73611000"}]},{"id":4301,"name":"Beltinci Municipality","native":null,"cities":[{"id":104063,"name":"Beltinci","native":null,"lat":"46.60528000","lon":"16.24056000"},{"id":104104,"name":"Gančani","native":null,"lat":"46.63250000","lon":"16.25111000"},{"id":104166,"name":"Lipovci","native":null,"lat":"46.62833000","lon":"16.22806000"},{"id":104331,"name":"Zgornje Gorje","native":null,"lat":"46.37962000","lon":"14.06937000"}]},{"id":4166,"name":"Benedikt Municipality","native":null,"cities":[{"id":104064,"name":"Benedikt","native":null,"lat":"46.60861000","lon":"15.88833000"}]},{"id":4179,"name":"Bistrica ob Sotli Municipality","native":null,"cities":[{"id":104067,"name":"Bistrica ob Sotli","native":null,"lat":"46.05889000","lon":"15.66417000"}]},{"id":4202,"name":"Bled Municipality","native":null,"cities":[{"id":104069,"name":"Bled","native":null,"lat":"46.36917000","lon":"14.11361000"},{"id":104144,"name":"Kostanjevica na Krki","native":null,"lat":"45.84611000","lon":"15.42222000"},{"id":104326,"name":"Zasip","native":null,"lat":"46.39284000","lon":"14.10869000"}]},{"id":4278,"name":"Bloke Municipality","native":null,"cities":[{"id":104207,"name":"Nova Vas","native":null,"lat":"45.77167000","lon":"14.50583000"}]},{"id":4282,"name":"Bohinj Municipality","native":null,"cities":[{"id":104070,"name":"Bohinjska Bistrica","native":null,"lat":"46.27216000","lon":"13.95350000"},{"id":104100,"name":"Dragomer","native":null,"lat":"46.01667000","lon":"14.38333000"},{"id":104172,"name":"Log pri Brezovici","native":null,"lat":"46.01667000","lon":"14.36667000"}]},{"id":4200,"name":"Borovnica Municipality","native":null,"cities":[{"id":104071,"name":"Borovnica","native":null,"lat":"45.91583000","lon":"14.36306000"},{"id":104180,"name":"Makole","native":null,"lat":"46.31722000","lon":"15.66722000"}]},{"id":4181,"name":"Bovec Municipality","native":null,"cities":[{"id":104072,"name":"Bovec","native":null,"lat":"46.33808000","lon":"13.55245000"},{"id":104190,"name":"Mirna","native":null,"lat":"45.95528000","lon":"15.06194000"}]},{"id":4141,"name":"Braslovče Municipality","native":null,"cities":[{"id":104073,"name":"Braslovče","native":null,"lat":"46.28972000","lon":"15.03889000"}]},{"id":4240,"name":"Brda Municipality","native":null,"cities":[{"id":104094,"name":"Dobrovo","native":null,"lat":"45.99639000","lon":"13.52639000"},{"id":104195,"name":"Mokronog","native":null,"lat":"45.93417000","lon":"15.14083000"}]},{"id":4215,"name":"Brežice Municipality","native":null,"cities":[{"id":104076,"name":"Brežice","native":null,"lat":"45.90333000","lon":"15.59111000"},{"id":104227,"name":"Poljčane","native":null,"lat":"46.31194000","lon":"15.57917000"}]},{"id":4165,"name":"Brezovica Municipality","native":null,"cities":[{"id":104075,"name":"Brezovica pri Ljubljani","native":null,"lat":"46.03333000","lon":"14.40000000"},{"id":104205,"name":"Notranje Gorice","native":null,"lat":"45.98750000","lon":"14.39889000"},{"id":104214,"name":"Opština Ljubljana-Vič-Rudnik","native":null,"lat":"46.03333000","lon":"14.41667000"},{"id":104254,"name":"Rečica ob Savinji","native":null,"lat":"46.31667000","lon":"14.91667000"},{"id":104316,"name":"Vnanje Gorice","native":null,"lat":"46.00722000","lon":"14.42194000"}]},{"id":4147,"name":"Cankova Municipality","native":null,"cities":[{"id":104078,"name":"Cankova","native":null,"lat":"46.72083000","lon":"16.02250000"}]},{"id":4310,"name":"Cerklje na Gorenjskem Municipality","native":null,"cities":[{"id":104080,"name":"Cerklje na Gorenjskem","native":null,"lat":"46.25417000","lon":"14.48861000"}]},{"id":4162,"name":"Cerknica Municipality","native":null,"cities":[{"id":104081,"name":"Cerknica","native":null,"lat":"45.79306000","lon":"14.36250000"},{"id":104246,"name":"Rakek","native":null,"lat":"45.81333000","lon":"14.31111000"}]},{"id":4178,"name":"Cerkno Municipality","native":null,"cities":[{"id":104082,"name":"Cerkno","native":null,"lat":"46.12556000","lon":"13.98167000"}]},{"id":4176,"name":"Cerkvenjak Municipality","native":null,"cities":[{"id":104083,"name":"Cerkvenjak","native":null,"lat":"46.57056000","lon":"15.94361000"}]},{"id":4191,"name":"City Municipality of Celje","native":null,"cities":[{"id":104079,"name":"Celje","native":null,"lat":"46.23092000","lon":"15.26044000"},{"id":104168,"name":"Ljubečna","native":null,"lat":"46.25567000","lon":"15.32430000"},{"id":104299,"name":"Trnovlje pri Celju","native":null,"lat":"46.25667000","lon":"15.29528000"}]},{"id":4236,"name":"City Municipality of Novo Mesto","native":null,"cities":[{"id":104208,"name":"Novo Mesto","native":null,"lat":"45.80397000","lon":"15.16886000"}]},{"id":4151,"name":"Črenšovci Municipality","native":null,"cities":[{"id":104337,"name":"Črenšovci","native":null,"lat":"46.55794000","lon":"16.30410000"}]},{"id":4232,"name":"Črna na Koroškem Municipality","native":null,"cities":[{"id":104338,"name":"Črna na Koroškem","native":null,"lat":"46.47045000","lon":"14.85009000"}]},{"id":4291,"name":"Črnomelj Municipality","native":null,"cities":[{"id":104339,"name":"Črnomelj","native":null,"lat":"45.57111000","lon":"15.18889000"}]},{"id":4304,"name":"Destrnik Municipality","native":null,"cities":[{"id":104087,"name":"Destrnik","native":null,"lat":"46.49254000","lon":"15.87893000"}]},{"id":4167,"name":"Divača Municipality","native":null,"cities":[{"id":104088,"name":"Divača","native":null,"lat":"45.68472000","lon":"13.97028000"}]},{"id":4295,"name":"Dobje Municipality","native":null,"cities":[{"id":104090,"name":"Dobje pri Planini","native":null,"lat":"46.13747000","lon":"15.39412000"}]},{"id":4216,"name":"Dobrepolje Municipality","native":null,"cities":[{"id":104309,"name":"Videm","native":null,"lat":"45.85000000","lon":"14.69417000"}]},{"id":4252,"name":"Dobrna Municipality","native":null,"cities":[{"id":104091,"name":"Dobrna","native":null,"lat":"46.33750000","lon":"15.22639000"}]},{"id":4308,"name":"Dobrova–Polhov Gradec Municipality","native":null,"cities":[{"id":104092,"name":"Dobrova","native":null,"lat":"46.04580000","lon":"14.39186000"}]},{"id":4189,"name":"Dobrovnik Municipality","native":null,"cities":[{"id":104093,"name":"Dobrovnik","native":null,"lat":"46.65139000","lon":"16.35250000"}]},{"id":4173,"name":"Dol pri Ljubljani Municipality","native":null,"cities":[{"id":104096,"name":"Dol pri Ljubljani","native":null,"lat":"46.08861000","lon":"14.60083000"}]},{"id":4281,"name":"Dolenjske Toplice Municipality","native":null,"cities":[{"id":104097,"name":"Dolenjske Toplice","native":null,"lat":"45.75657000","lon":"15.05917000"}]},{"id":4159,"name":"Domžale Municipality","native":null,"cities":[{"id":104089,"name":"Dob","native":null,"lat":"46.15194000","lon":"14.62861000"},{"id":104098,"name":"Domžale","native":null,"lat":"46.13774000","lon":"14.59371000"},{"id":104244,"name":"Radomlje","native":null,"lat":"46.17361000","lon":"14.61222000"},{"id":104312,"name":"Vir","native":null,"lat":"46.15325000","lon":"14.60741000"}]},{"id":4290,"name":"Dornava Municipality","native":null,"cities":[{"id":104099,"name":"Dornava","native":null,"lat":"46.43667000","lon":"15.95361000"}]},{"id":4345,"name":"Dravograd Municipality","native":null,"cities":[{"id":104102,"name":"Dravograd","native":null,"lat":"46.58806000","lon":"15.01917000"}]},{"id":4213,"name":"Duplek Municipality","native":null,"cities":[{"id":104283,"name":"Spodnji Duplek","native":null,"lat":"46.50306000","lon":"15.74528000"},{"id":104334,"name":"Zgornji Duplek","native":null,"lat":"46.51361000","lon":"15.72083000"}]},{"id":4293,"name":"Gorenja Vas–Poljane Municipality","native":null,"cities":[{"id":104106,"name":"Gorenja Vas","native":null,"lat":"46.10722000","lon":"14.14806000"}]},{"id":4210,"name":"Gorišnica Municipality","native":null,"cities":[{"id":104107,"name":"Gorišnica","native":null,"lat":"46.41472000","lon":"16.01389000"}]},{"id":4284,"name":"Gorje Municipality","native":null,"cities":[]},{"id":4343,"name":"Gornja Radgona Municipality","native":null,"cities":[{"id":104108,"name":"Gornja Radgona","native":null,"lat":"46.67333000","lon":"15.99222000"}]},{"id":4339,"name":"Gornji Grad Municipality","native":null,"cities":[{"id":104109,"name":"Gornji Grad","native":null,"lat":"46.29528000","lon":"14.80833000"}]},{"id":4271,"name":"Gornji Petrovci Municipality","native":null,"cities":[{"id":104110,"name":"Gornji Petrovci","native":null,"lat":"46.80528000","lon":"16.22250000"}]},{"id":4217,"name":"Grad Municipality","native":null,"cities":[{"id":104112,"name":"Grad","native":null,"lat":"46.80000000","lon":"16.10000000"}]},{"id":4336,"name":"Grosuplje Municipality","native":null,"cities":[{"id":104113,"name":"Grosuplje","native":null,"lat":"45.95556000","lon":"14.65889000"},{"id":104357,"name":"Šmarje-Sap","native":null,"lat":"45.97618000","lon":"14.61177000"}]},{"id":4145,"name":"Hajdina Municipality","native":null,"cities":[{"id":104279,"name":"Spodnja Hajdina","native":null,"lat":"46.40889000","lon":"15.84694000"}]},{"id":4175,"name":"Hoče–Slivnica Municipality","native":null,"cities":[{"id":104116,"name":"Hotinja Vas","native":null,"lat":"46.46667000","lon":"15.66667000"},{"id":104242,"name":"Radizel","native":null,"lat":"46.47444000","lon":"15.65583000"},{"id":104260,"name":"Rogoza","native":null,"lat":"46.50000000","lon":"15.68333000"},{"id":104281,"name":"Spodnje Hoče","native":null,"lat":"46.50000000","lon":"15.65000000"}]},{"id":4327,"name":"Hodoš Municipality","native":null,"cities":[{"id":104114,"name":"Hodoš","native":null,"lat":"46.82333000","lon":"16.33417000"}]},{"id":4193,"name":"Horjul Municipality","native":null,"cities":[{"id":104115,"name":"Horjul","native":null,"lat":"46.02361000","lon":"14.29917000"}]},{"id":4341,"name":"Hrastnik Municipality","native":null,"cities":[{"id":104095,"name":"Dol pri Hrastniku","native":null,"lat":"46.14194000","lon":"15.11278000"},{"id":104118,"name":"Hrastnik","native":null,"lat":"46.14611000","lon":"15.08139000"}]},{"id":4321,"name":"Hrpelje–Kozina Municipality","native":null,"cities":[{"id":104147,"name":"Kozina","native":null,"lat":"45.61000000","lon":"13.93556000"}]},{"id":4152,"name":"Idrija Municipality","native":null,"cities":[{"id":104122,"name":"Idrija","native":null,"lat":"46.00278000","lon":"14.03056000"},{"id":104280,"name":"Spodnja Idrija","native":null,"lat":"46.03194000","lon":"14.02722000"}]},{"id":4286,"name":"Ig Municipality","native":null,"cities":[{"id":104123,"name":"Ig","native":null,"lat":"45.96028000","lon":"14.52889000"}]},{"id":4305,"name":"Ivančna Gorica Municipality","native":null,"cities":[{"id":104125,"name":"Ivančna Gorica","native":null,"lat":"45.93833000","lon":"14.80444000"},{"id":104350,"name":"Šentvid pri Stični","native":null,"lat":"45.95004000","lon":"14.84344000"}]},{"id":4322,"name":"Izola Municipality","native":null,"cities":[{"id":104127,"name":"Izola","native":null,"lat":"45.53694000","lon":"13.66194000"},{"id":104128,"name":"Jagodje","native":null,"lat":"45.52845000","lon":"13.64721000"}]},{"id":4337,"name":"Jesenice Municipality","native":null,"cities":[{"id":104120,"name":"Hrušica","native":null,"lat":"46.44500000","lon":"14.01778000"},{"id":104130,"name":"Jesenice","native":null,"lat":"46.43056000","lon":"14.06694000"},{"id":104143,"name":"Koroška Bela","native":null,"lat":"46.44913000","lon":"14.11135000"},{"id":104274,"name":"Slovenski Javornik","native":null,"lat":"46.42611000","lon":"14.08722000"}]},{"id":4203,"name":"Jezersko Municipality","native":null,"cities":[{"id":104332,"name":"Zgornje Jezersko","native":null,"lat":"46.39410000","lon":"14.50659000"}]},{"id":4266,"name":"Juršinci Municipality","native":null,"cities":[{"id":104131,"name":"Juršinci","native":null,"lat":"46.48472000","lon":"15.97139000"}]},{"id":4180,"name":"Kamnik Municipality","native":null,"cities":[{"id":104133,"name":"Kamnik","native":null,"lat":"46.22587000","lon":"14.61207000"},{"id":104184,"name":"Mekinje","native":null,"lat":"46.23333000","lon":"14.61667000"},{"id":104355,"name":"Šmarca","native":null,"lat":"46.19333000","lon":"14.59667000"}]},{"id":4227,"name":"Kanal ob Soči Municipality","native":null,"cities":[{"id":104086,"name":"Deskle","native":null,"lat":"46.05307000","lon":"13.61382000"},{"id":104134,"name":"Kanal","native":null,"lat":"46.08861000","lon":"13.63972000"}]},{"id":4150,"name":"Kidričevo Municipality","native":null,"cities":[{"id":104135,"name":"Kidričevo","native":null,"lat":"46.40361000","lon":"15.79111000"}]},{"id":4243,"name":"Kobarid Municipality","native":null,"cities":[{"id":104137,"name":"Kobarid","native":null,"lat":"46.24761000","lon":"13.57907000"}]},{"id":4325,"name":"Kobilje Municipality","native":null,"cities":[{"id":104138,"name":"Kobilje","native":null,"lat":"46.68472000","lon":"16.39778000"}]},{"id":4335,"name":"Kočevje Municipality","native":null,"cities":[{"id":104149,"name":"Kočevje","native":null,"lat":"45.64333000","lon":"14.86333000"}]},{"id":4315,"name":"Komen Municipality","native":null,"cities":[{"id":104140,"name":"Komen","native":null,"lat":"45.81528000","lon":"13.74833000"}]},{"id":4283,"name":"Komenda Municipality","native":null,"cities":[{"id":104141,"name":"Komenda","native":null,"lat":"46.20484000","lon":"14.53839000"},{"id":104199,"name":"Moste","native":null,"lat":"46.19500000","lon":"14.55139000"}]},{"id":4319,"name":"Koper City Municipality","native":null,"cities":[{"id":104085,"name":"Dekani","native":null,"lat":"45.54972000","lon":"13.81361000"},{"id":104121,"name":"Hrvatini","native":null,"lat":"45.58278000","lon":"13.75667000"},{"id":104142,"name":"Koper","native":null,"lat":"45.54694000","lon":"13.72944000"},{"id":104223,"name":"Pobegi","native":null,"lat":"45.53944000","lon":"13.79611000"},{"id":104231,"name":"Prade","native":null,"lat":"45.54003000","lon":"13.77607000"},{"id":104282,"name":"Spodnje Škofije","native":null,"lat":"45.57167000","lon":"13.79250000"},{"id":104288,"name":"Sv. Anton","native":null,"lat":"45.52583000","lon":"13.83194000"}]},{"id":4254,"name":"Kostanjevica na Krki Municipality","native":null,"cities":[]},{"id":4331,"name":"Kostel Municipality","native":null,"cities":[{"id":104145,"name":"Kostel","native":null,"lat":"45.50842000","lon":"14.91005000"}]},{"id":4186,"name":"Kozje Municipality","native":null,"cities":[{"id":104148,"name":"Kozje","native":null,"lat":"46.07500000","lon":"15.56028000"}]},{"id":4287,"name":"Kranj City Municipality","native":null,"cities":[{"id":104077,"name":"Britof","native":null,"lat":"46.26024000","lon":"14.39037000"},{"id":104105,"name":"Golnik","native":null,"lat":"46.33333000","lon":"14.33333000"},{"id":104139,"name":"Kokrica","native":null,"lat":"46.27028000","lon":"14.36111000"},{"id":104150,"name":"Kranj","native":null,"lat":"46.23887000","lon":"14.35561000"},{"id":104193,"name":"Mlaka pri Kranju","native":null,"lat":"46.28333000","lon":"14.35000000"},{"id":104330,"name":"Zgornje Bitnje","native":null,"lat":"46.22000000","lon":"14.33667000"}]},{"id":4340,"name":"Kranjska Gora Municipality","native":null,"cities":[{"id":104151,"name":"Kranjska Gora","native":null,"lat":"46.45689000","lon":"13.77824000"},{"id":104194,"name":"Mojstrana","native":null,"lat":"46.42383000","lon":"13.87520000"}]},{"id":4238,"name":"Križevci Municipality","native":null,"cities":[{"id":104152,"name":"Križevci pri Ljutomeru","native":null,"lat":"46.56833000","lon":"16.13861000"}]},{"id":4197,"name":"Kungota","native":null,"cities":[{"id":104328,"name":"Zgornja Kungota","native":null,"lat":"46.63917000","lon":"15.61556000"}]},{"id":4211,"name":"Kuzma Municipality","native":null,"cities":[{"id":104156,"name":"Kuzma","native":null,"lat":"46.83694000","lon":"16.08333000"}]},{"id":4338,"name":"Laško Municipality","native":null,"cities":[{"id":104158,"name":"Laško","native":null,"lat":"46.15463000","lon":"15.23555000"}]},{"id":4142,"name":"Lenart Municipality","native":null,"cities":[{"id":104160,"name":"Lenart v Slov. Goricah","native":null,"lat":"46.57611000","lon":"15.83139000"}]},{"id":4225,"name":"Lendava Municipality","native":null,"cities":[{"id":104161,"name":"Lendava","native":null,"lat":"46.56494000","lon":"16.45091000"}]},{"id":4347,"name":"Litija Municipality","native":null,"cities":[{"id":104167,"name":"Litija","native":null,"lat":"46.05861000","lon":"14.82250000"}]},{"id":4270,"name":"Ljubljana City Municipality","native":null,"cities":[{"id":104101,"name":"Dravlje District","native":null,"lat":"46.07290000","lon":"14.44741000"},{"id":104129,"name":"Jarše District","native":null,"lat":"46.07345000","lon":"14.55431000"},{"id":104169,"name":"Ljubljana","native":null,"lat":"46.05108000","lon":"14.50513000"},{"id":104211,"name":"Opčina Ljubljana-Bežigrad","native":null,"lat":"46.08333000","lon":"14.53333000"},{"id":104212,"name":"Opština Ljubljana-Center","native":null,"lat":"46.05000000","lon":"14.53333000"},{"id":104213,"name":"Opština Ljubljana-Moste-Polje","native":null,"lat":"46.06667000","lon":"14.61667000"},{"id":104262,"name":"Rožnik District","native":null,"lat":"46.05999000","lon":"14.46779000"},{"id":104349,"name":"Šentvid District","native":null,"lat":"46.10559000","lon":"14.43329000"},{"id":104278,"name":"Sostro District","native":null,"lat":"46.04341000","lon":"14.67293000"},{"id":104300,"name":"Trnovo District","native":null,"lat":"46.02412000","lon":"14.48891000"},{"id":104315,"name":"Vič District","native":null,"lat":"46.00779000","lon":"14.46968000"}]},{"id":4294,"name":"Ljubno Municipality","native":null,"cities":[{"id":104170,"name":"Ljubno ob Savinji","native":null,"lat":"46.34358000","lon":"14.83377000"}]},{"id":4351,"name":"Ljutomer Municipality","native":null,"cities":[{"id":104171,"name":"Ljutomer","native":null,"lat":"46.52083000","lon":"16.19750000"}]},{"id":4306,"name":"Log–Dragomer Municipality","native":null,"cities":[]},{"id":4350,"name":"Logatec Municipality","native":null,"cities":[{"id":104173,"name":"Logatec","native":null,"lat":"45.91444000","lon":"14.22583000"}]},{"id":4174,"name":"Loška Dolina Municipality","native":null,"cities":[{"id":104163,"name":"Leskova Dolina","native":null,"lat":"45.62139000","lon":"14.46056000"}]},{"id":4158,"name":"Loški Potok Municipality","native":null,"cities":[{"id":104119,"name":"Hrib-Loški Potok","native":null,"lat":"45.70688000","lon":"14.61674000"}]},{"id":4156,"name":"Lovrenc na Pohorju Municipality","native":null,"cities":[{"id":104175,"name":"Lovrenc na Pohorju","native":null,"lat":"46.54056000","lon":"15.39306000"}]},{"id":4219,"name":"Luče Municipality","native":null,"cities":[{"id":104178,"name":"Luče","native":null,"lat":"46.35611000","lon":"14.74667000"}]},{"id":4302,"name":"Lukovica Municipality","native":null,"cities":[{"id":104177,"name":"Lukovica pri Domžalah","native":null,"lat":"46.16988000","lon":"14.69179000"}]},{"id":4157,"name":"Majšperk Municipality","native":null,"cities":[{"id":104179,"name":"Majšperk","native":null,"lat":"46.35167000","lon":"15.73361000"}]},{"id":4224,"name":"Makole Municipality","native":null,"cities":[]},{"id":4242,"name":"Maribor City Municipality","native":null,"cities":[{"id":104074,"name":"Bresternica","native":null,"lat":"46.56972000","lon":"15.57500000"},{"id":104132,"name":"Kamnica","native":null,"lat":"46.57444000","lon":"15.61417000"},{"id":104165,"name":"Limbuš","native":null,"lat":"46.55361000","lon":"15.58361000"},{"id":104181,"name":"Maribor","native":null,"lat":"46.55472000","lon":"15.64667000"},{"id":104219,"name":"Pekre","native":null,"lat":"46.54722000","lon":"15.59556000"},{"id":104251,"name":"Razvanje","native":null,"lat":"46.51444000","lon":"15.63611000"}]},{"id":4244,"name":"Markovci Municipality","native":null,"cities":[{"id":104182,"name":"Markovci","native":null,"lat":"46.39557000","lon":"15.92831000"}]},{"id":4349,"name":"Medvode Municipality","native":null,"cities":[{"id":104183,"name":"Medvode","native":null,"lat":"46.14220000","lon":"14.41114000"},{"id":104215,"name":"Opština [historical] Ljubljana-Šiška","native":null,"lat":"46.16667000","lon":"14.43333000"},{"id":104333,"name":"Zgornje Pirniče","native":null,"lat":"46.14251000","lon":"14.43158000"}]},{"id":4348,"name":"Mengeš Municipality","native":null,"cities":[{"id":104185,"name":"Mengeš","native":null,"lat":"46.16694000","lon":"14.57500000"},{"id":104235,"name":"Preserje pri Radomljah","native":null,"lat":"46.16911000","lon":"14.59698000"}]},{"id":4323,"name":"Metlika Municipality","native":null,"cities":[{"id":104186,"name":"Metlika","native":null,"lat":"45.64722000","lon":"15.31417000"}]},{"id":4265,"name":"Mežica Municipality","native":null,"cities":[{"id":104187,"name":"Mežica","native":null,"lat":"46.52139000","lon":"14.85444000"}]},{"id":4223,"name":"Miklavž na Dravskem Polju Municipality","native":null,"cities":[{"id":104188,"name":"Miklavž na Dravskem Polju","native":null,"lat":"46.50583000","lon":"15.69722000"}]},{"id":4220,"name":"Miren–Kostanjevica Municipality","native":null,"cities":[{"id":104065,"name":"Bilje","native":null,"lat":"45.89444000","lon":"13.63222000"},{"id":104189,"name":"Miren","native":null,"lat":"45.89556000","lon":"13.60750000"}]},{"id":4298,"name":"Mirna Municipality","native":null,"cities":[]},{"id":4237,"name":"Mirna Peč Municipality","native":null,"cities":[{"id":104191,"name":"Mirna Peč","native":null,"lat":"45.86028000","lon":"15.08333000"}]},{"id":4212,"name":"Mislinja Municipality","native":null,"cities":[{"id":104192,"name":"Mislinja","native":null,"lat":"46.44141000","lon":"15.20027000"}]},{"id":4297,"name":"Mokronog–Trebelno Municipality","native":null,"cities":[]},{"id":4168,"name":"Moravče Municipality","native":null,"cities":[{"id":104197,"name":"Moravče","native":null,"lat":"46.13694000","lon":"14.74500000"}]},{"id":4218,"name":"Moravske Toplice Municipality","native":null,"cities":[{"id":104196,"name":"Moravske Toplice","native":null,"lat":"46.68313000","lon":"16.22080000"}]},{"id":4190,"name":"Mozirje Municipality","native":null,"cities":[{"id":104200,"name":"Mozirje","native":null,"lat":"46.33944000","lon":"14.96333000"}]},{"id":4318,"name":"Municipality of Apače","native":null,"cities":[{"id":104061,"name":"Apače","native":null,"lat":"46.69722000","lon":"15.91056000"}]},{"id":4309,"name":"Municipality of Cirkulane","native":null,"cities":[]},{"id":4344,"name":"Municipality of Ilirska Bistrica","native":null,"cities":[{"id":104124,"name":"Ilirska Bistrica","native":null,"lat":"45.56757000","lon":"14.24571000"}]},{"id":4314,"name":"Municipality of Krško","native":null,"cities":[{"id":104155,"name":"Krško","native":null,"lat":"45.95915000","lon":"15.49167000"},{"id":104164,"name":"Leskovec pri Krškem","native":null,"lat":"45.93566000","lon":"15.47184000"},{"id":104267,"name":"Senovo","native":null,"lat":"46.02361000","lon":"15.47694000"}]},{"id":4187,"name":"Municipality of Škofljica","native":null,"cities":[{"id":104157,"name":"Lavrica","native":null,"lat":"46.00002000","lon":"14.55730000"},{"id":104354,"name":"Škofljica","native":null,"lat":"45.98333000","lon":"14.57667000"}]},{"id":4313,"name":"Murska Sobota City Municipality","native":null,"cities":[{"id":104062,"name":"Bakovci","native":null,"lat":"46.61889000","lon":"16.15028000"},{"id":104336,"name":"Černelavci","native":null,"lat":"46.66667000","lon":"16.13333000"},{"id":104153,"name":"Krog","native":null,"lat":"46.63806000","lon":"16.14139000"},{"id":104201,"name":"Murska Sobota","native":null,"lat":"46.66250000","lon":"16.16639000"},{"id":104247,"name":"Rakičan","native":null,"lat":"46.65167000","lon":"16.20417000"}]},{"id":4208,"name":"Muta Municipality","native":null,"cities":[{"id":104202,"name":"Muta","native":null,"lat":"46.61139000","lon":"15.16611000"}]},{"id":4177,"name":"Naklo Municipality","native":null,"cities":[{"id":104203,"name":"Naklo","native":null,"lat":"46.27278000","lon":"14.31722000"}]},{"id":4329,"name":"Nazarje Municipality","native":null,"cities":[{"id":104204,"name":"Nazarje","native":null,"lat":"46.31757000","lon":"14.94674000"}]},{"id":4205,"name":"Nova Gorica City Municipality","native":null,"cities":[{"id":104154,"name":"Kromberk","native":null,"lat":"45.96083000","lon":"13.66556000"},{"id":104206,"name":"Nova Gorica","native":null,"lat":"45.95604000","lon":"13.64837000"},{"id":104237,"name":"Prvačina","native":null,"lat":"45.89000000","lon":"13.71806000"},{"id":104342,"name":"Šempas","native":null,"lat":"45.93028000","lon":"13.74361000"},{"id":104276,"name":"Solkan","native":null,"lat":"45.97139000","lon":"13.64944000"}]},{"id":4320,"name":"Odranci Municipality","native":null,"cities":[{"id":104209,"name":"Odranci","native":null,"lat":"46.58667000","lon":"16.28028000"}]},{"id":4143,"name":"Oplotnica","native":null,"cities":[{"id":104210,"name":"Oplotnica","native":null,"lat":"46.38778000","lon":"15.44667000"}]},{"id":4221,"name":"Ormož Municipality","native":null,"cities":[{"id":104216,"name":"Ormož","native":null,"lat":"46.41139000","lon":"16.15444000"}]},{"id":4199,"name":"Osilnica Municipality","native":null,"cities":[{"id":104217,"name":"Osilnica","native":null,"lat":"45.52914000","lon":"14.69838000"}]},{"id":4172,"name":"Pesnica Municipality","native":null,"cities":[{"id":104220,"name":"Pesnica pri Mariboru","native":null,"lat":"46.60694000","lon":"15.67667000"}]},{"id":4201,"name":"Piran Municipality","native":null,"cities":[{"id":104176,"name":"Lucija","native":null,"lat":"45.50526000","lon":"13.60240000"},{"id":104221,"name":"Piran","native":null,"lat":"45.52778000","lon":"13.57056000"},{"id":104229,"name":"Portorož","native":null,"lat":"45.51429000","lon":"13.59206000"},{"id":104269,"name":"Seča","native":null,"lat":"45.49584000","lon":"13.61466000"}]},{"id":4184,"name":"Pivka Municipality","native":null,"cities":[{"id":104222,"name":"Pivka","native":null,"lat":"45.68292000","lon":"14.19588000"}]},{"id":4146,"name":"Podčetrtek Municipality","native":null,"cities":[{"id":104226,"name":"Podčetrtek","native":null,"lat":"46.15694000","lon":"15.59861000"}]},{"id":4161,"name":"Podlehnik Municipality","native":null,"cities":[{"id":104224,"name":"Podlehnik","native":null,"lat":"46.33528000","lon":"15.88000000"}]},{"id":4234,"name":"Podvelka Municipality","native":null,"cities":[{"id":104225,"name":"Podvelka","native":null,"lat":"46.58694000","lon":"15.33056000"}]},{"id":4239,"name":"Poljčane Municipality","native":null,"cities":[]},{"id":4272,"name":"Polzela Municipality","native":null,"cities":[{"id":104228,"name":"Polzela","native":null,"lat":"46.28333000","lon":"15.06667000"}]},{"id":4330,"name":"Postojna Municipality","native":null,"cities":[{"id":104230,"name":"Postojna","native":null,"lat":"45.77435000","lon":"14.21528000"}]},{"id":4188,"name":"Prebold Municipality","native":null,"cities":[{"id":104233,"name":"Prebold","native":null,"lat":"46.23694000","lon":"15.09250000"}]},{"id":4303,"name":"Preddvor Municipality","native":null,"cities":[{"id":104234,"name":"Preddvor","native":null,"lat":"46.30250000","lon":"14.42306000"}]},{"id":4274,"name":"Prevalje Municipality","native":null,"cities":[{"id":104236,"name":"Prevalje","native":null,"lat":"46.54694000","lon":"14.92083000"}]},{"id":4228,"name":"Ptuj City Municipality","native":null,"cities":[{"id":104238,"name":"Ptuj","native":null,"lat":"46.42005000","lon":"15.87018000"}]},{"id":4288,"name":"Puconci Municipality","native":null,"cities":[{"id":104239,"name":"Puconci","native":null,"lat":"46.70667000","lon":"16.15639000"}]},{"id":4204,"name":"Rače–Fram Municipality","native":null,"cities":[{"id":104103,"name":"Fram","native":null,"lat":"46.45600000","lon":"15.63007000"},{"id":104198,"name":"Morje","native":null,"lat":"46.44444000","lon":"15.62139000"},{"id":104252,"name":"Rače","native":null,"lat":"46.45194000","lon":"15.68139000"}]},{"id":4195,"name":"Radeče Municipality","native":null,"cities":[{"id":104241,"name":"Radeče","native":null,"lat":"46.06806000","lon":"15.18389000"}]},{"id":4292,"name":"Radenci Municipality","native":null,"cities":[{"id":104240,"name":"Radenci","native":null,"lat":"46.64201000","lon":"16.03781000"}]},{"id":4275,"name":"Radlje ob Dravi Municipality","native":null,"cities":[{"id":104243,"name":"Radlje ob Dravi","native":null,"lat":"46.61417000","lon":"15.22639000"}]},{"id":4231,"name":"Radovljica Municipality","native":null,"cities":[{"id":104162,"name":"Lesce","native":null,"lat":"46.36111000","lon":"14.15778000"},{"id":104245,"name":"Radovljica","native":null,"lat":"46.34444000","lon":"14.17444000"}]},{"id":4155,"name":"Ravne na Koroškem Municipality","native":null,"cities":[{"id":104146,"name":"Kotlje","native":null,"lat":"46.52139000","lon":"14.98694000"},{"id":104249,"name":"Ravne na Koroškem","native":null,"lat":"46.54306000","lon":"14.96917000"}]},{"id":4206,"name":"Razkrižje Municipality","native":null,"cities":[{"id":104250,"name":"Razkrižje","native":null,"lat":"46.52167000","lon":"16.28111000"}]},{"id":4160,"name":"Rečica ob Savinji Municipality","native":null,"cities":[]},{"id":4253,"name":"Renče–Vogrsko Municipality","native":null,"cities":[{"id":104253,"name":"Renče","native":null,"lat":"45.89000000","lon":"13.66861000"},{"id":104319,"name":"Volčja Draga","native":null,"lat":"45.90694000","lon":"13.67750000"}]},{"id":4235,"name":"Ribnica Municipality","native":null,"cities":[{"id":104255,"name":"Ribnica","native":null,"lat":"45.73861000","lon":"14.72750000"}]},{"id":4207,"name":"Ribnica na Pohorju Municipality","native":null,"cities":[{"id":104256,"name":"Ribnica na Pohorju","native":null,"lat":"46.53500000","lon":"15.27278000"}]},{"id":4233,"name":"Rogaška Slatina Municipality","native":null,"cities":[{"id":104258,"name":"Rogaška Slatina","native":null,"lat":"46.23750000","lon":"15.63972000"}]},{"id":4264,"name":"Rogašovci Municipality","native":null,"cities":[{"id":104259,"name":"Rogašovci","native":null,"lat":"46.80000000","lon":"16.03333000"}]},{"id":4209,"name":"Rogatec Municipality","native":null,"cities":[{"id":104257,"name":"Rogatec","native":null,"lat":"46.22944000","lon":"15.70028000"}]},{"id":4280,"name":"Ruše Municipality","native":null,"cities":[{"id":104066,"name":"Bistrica ob Dravi","native":null,"lat":"46.55419000","lon":"15.54855000"},{"id":104263,"name":"Ruše","native":null,"lat":"46.53944000","lon":"15.51583000"}]},{"id":4222,"name":"Šalovci Municipality","native":null,"cities":[{"id":104341,"name":"Šalovci","native":null,"lat":"46.82500000","lon":"16.29806000"}]},{"id":4230,"name":"Selnica ob Dravi Municipality","native":null,"cities":[{"id":104264,"name":"Selnica ob Dravi","native":null,"lat":"46.55000000","lon":"15.49500000"}]},{"id":4346,"name":"Semič Municipality","native":null,"cities":[{"id":104266,"name":"Semič","native":null,"lat":"45.64611000","lon":"15.18222000"}]},{"id":4317,"name":"Šempeter–Vrtojba Municipality","native":null,"cities":[{"id":104261,"name":"Rožna Dolina","native":null,"lat":"45.94194000","lon":"13.66779000"},{"id":104343,"name":"Šempeter pri Gorici","native":null,"lat":"45.92750000","lon":"13.64111000"},{"id":104322,"name":"Vrtojba","native":null,"lat":"45.91250000","lon":"13.63417000"}]},{"id":4299,"name":"Šenčur Municipality","native":null,"cities":[{"id":104117,"name":"Hrastje","native":null,"lat":"46.21667000","lon":"14.40000000"},{"id":104351,"name":"Šenčur","native":null,"lat":"46.24556000","lon":"14.41972000"}]},{"id":4324,"name":"Šentilj Municipality","native":null,"cities":[{"id":104265,"name":"Selnica ob Muri","native":null,"lat":"46.68333000","lon":"15.70000000"},{"id":104345,"name":"Šentilj v Slov. Goricah","native":null,"lat":"46.68167000","lon":"15.64806000"}]},{"id":4241,"name":"Šentjernej Municipality","native":null,"cities":[{"id":104346,"name":"Šentjernej","native":null,"lat":"45.84000000","lon":"15.33611000"}]},{"id":4171,"name":"Šentjur Municipality","native":null,"cities":[{"id":104347,"name":"Šentjur","native":null,"lat":"46.21722000","lon":"15.39750000"}]},{"id":4311,"name":"Šentrupert Municipality","native":null,"cities":[{"id":104348,"name":"Šentrupert","native":null,"lat":"45.97778000","lon":"15.09556000"}]},{"id":4268,"name":"Sevnica Municipality","native":null,"cities":[{"id":104268,"name":"Sevnica","native":null,"lat":"46.00778000","lon":"15.31556000"}]},{"id":4149,"name":"Sežana Municipality","native":null,"cities":[{"id":104270,"name":"Sežana","native":null,"lat":"45.70924000","lon":"13.87333000"}]},{"id":4170,"name":"Škocjan Municipality","native":null,"cities":[{"id":104352,"name":"Škocjan","native":null,"lat":"45.90667000","lon":"15.29139000"}]},{"id":4316,"name":"Škofja Loka Municipality","native":null,"cities":[{"id":104353,"name":"Škofja Loka","native":null,"lat":"46.16551000","lon":"14.30626000"},{"id":104289,"name":"Sv. Duh","native":null,"lat":"46.18333000","lon":"14.33333000"}]},{"id":4169,"name":"Slovenj Gradec City Municipality","native":null,"cities":[{"id":104159,"name":"Legen","native":null,"lat":"46.50651000","lon":"15.14424000"},{"id":104218,"name":"Pameče","native":null,"lat":"46.53417000","lon":"15.07917000"},{"id":104271,"name":"Slovenj Gradec","native":null,"lat":"46.51028000","lon":"15.08056000"},{"id":104361,"name":"Šmartno pri Slovenj Gradcu","native":null,"lat":"46.48944000","lon":"15.10667000"}]},{"id":4332,"name":"Slovenska Bistrica Municipality","native":null,"cities":[{"id":104232,"name":"Pragersko","native":null,"lat":"46.39667000","lon":"15.66000000"},{"id":104272,"name":"Slovenska Bistrica","native":null,"lat":"46.39278000","lon":"15.57444000"},{"id":104329,"name":"Zgornja Polskava","native":null,"lat":"46.42556000","lon":"15.61222000"}]},{"id":4198,"name":"Slovenske Konjice Municipality","native":null,"cities":[{"id":104273,"name":"Slovenske Konjice","native":null,"lat":"46.33667000","lon":"15.42583000"}]},{"id":4285,"name":"Šmarje pri Jelšah Municipality","native":null,"cities":[{"id":104356,"name":"Šmarje pri Jelšah","native":null,"lat":"46.22722000","lon":"15.51917000"}]},{"id":4289,"name":"Šmarješke Toplice Municipality","native":null,"cities":[{"id":104358,"name":"Šmarjeta","native":null,"lat":"45.88333000","lon":"15.25000000"}]},{"id":4296,"name":"Šmartno ob Paki Municipality","native":null,"cities":[{"id":104359,"name":"Šmartno ob Paki","native":null,"lat":"46.33333000","lon":"15.03333000"}]},{"id":4279,"name":"Šmartno pri Litiji Municipality","native":null,"cities":[{"id":104360,"name":"Šmartno pri Litiji","native":null,"lat":"46.04444000","lon":"14.84417000"}]},{"id":4277,"name":"Sodražica Municipality","native":null,"cities":[{"id":104275,"name":"Sodražica","native":null,"lat":"45.76111000","lon":"14.63556000"}]},{"id":4261,"name":"Solčava Municipality","native":null,"cities":[{"id":104277,"name":"Solčava","native":null,"lat":"46.41944000","lon":"14.69361000"}]},{"id":4248,"name":"Šoštanj Municipality","native":null,"cities":[{"id":104248,"name":"Ravne","native":null,"lat":"46.41413000","lon":"15.06087000"},{"id":104362,"name":"Šoštanj","native":null,"lat":"46.38000000","lon":"15.04861000"},{"id":104296,"name":"Topolšica","native":null,"lat":"46.40028000","lon":"15.02157000"}]},{"id":4263,"name":"Središče ob Dravi","native":null,"cities":[{"id":104284,"name":"Središče ob Dravi","native":null,"lat":"46.39417000","lon":"16.26806000"}]},{"id":4259,"name":"Starše Municipality","native":null,"cities":[{"id":104285,"name":"Starše","native":null,"lat":"46.46583000","lon":"15.76722000"}]},{"id":4185,"name":"Štore Municipality","native":null,"cities":[{"id":104363,"name":"Štore","native":null,"lat":"46.22083000","lon":"15.31389000"}]},{"id":4333,"name":"Straža Municipality","native":null,"cities":[{"id":104286,"name":"Straža","native":null,"lat":"45.78000000","lon":"15.07278000"}]},{"id":4164,"name":"Sveta Ana Municipality","native":null,"cities":[{"id":104287,"name":"Sv. Ana v Slov. Goricah","native":null,"lat":"46.64917000","lon":"15.84417000"}]},{"id":4260,"name":"Sveta Trojica v Slovenskih Goricah Municipality","native":null,"cities":[{"id":104290,"name":"Sv. Trojica v Slov. Goricah","native":null,"lat":"46.57667000","lon":"15.87694000"}]},{"id":4229,"name":"Sveti Andraž v Slovenskih Goricah Municipality","native":null,"cities":[{"id":104314,"name":"Vitomarci","native":null,"lat":"46.52750000","lon":"15.93944000"}]},{"id":4255,"name":"Sveti Jurij ob Ščavnici Municipality","native":null,"cities":[]},{"id":4328,"name":"Sveti Jurij v Slovenskih Goricah Municipality","native":null,"cities":[{"id":104291,"name":"Sveti Jurij ob Ščavnici","native":null,"lat":"46.56950000","lon":"16.02347000"}]},{"id":4273,"name":"Sveti Tomaž Municipality","native":null,"cities":[{"id":104292,"name":"Sveti Tomaž","native":null,"lat":"46.48417000","lon":"16.08361000"}]},{"id":4194,"name":"Tabor Municipality","native":null,"cities":[{"id":104293,"name":"Tabor","native":null,"lat":"46.23611000","lon":"15.01833000"}]},{"id":4312,"name":"Tišina Municipality","native":null,"cities":[{"id":104294,"name":"Tišina","native":null,"lat":"46.65806000","lon":"16.09167000"}]},{"id":4247,"name":"Tolmin Municipality","native":null,"cities":[{"id":104295,"name":"Tolmin","native":null,"lat":"46.18304000","lon":"13.73321000"}]},{"id":4246,"name":"Trbovlje Municipality","native":null,"cities":[{"id":104297,"name":"Trbovlje","native":null,"lat":"46.15500000","lon":"15.05333000"}]},{"id":4214,"name":"Trebnje Municipality","native":null,"cities":[{"id":104298,"name":"Trebnje","native":null,"lat":"45.90417000","lon":"15.02167000"}]},{"id":4153,"name":"Trnovska Vas Municipality","native":null,"cities":[{"id":104301,"name":"Trnovska Vas","native":null,"lat":"46.52019000","lon":"15.88657000"}]},{"id":4250,"name":"Tržič Municipality","native":null,"cities":[{"id":104068,"name":"Bistrica pri Tržiču","native":null,"lat":"46.35472000","lon":"14.29167000"},{"id":104303,"name":"Tržič","native":null,"lat":"46.36357000","lon":"14.31046000"}]},{"id":4334,"name":"Trzin Municipality","native":null,"cities":[{"id":104340,"name":"Črnuče District","native":null,"lat":"46.11506000","lon":"14.55371000"},{"id":104302,"name":"Trzin","native":null,"lat":"46.13333000","lon":"14.56667000"}]},{"id":4251,"name":"Turnišče Municipality","native":null,"cities":[{"id":104304,"name":"Turnišče","native":null,"lat":"46.62778000","lon":"16.32028000"}]},{"id":4267,"name":"Velika Polana Municipality","native":null,"cities":[{"id":104305,"name":"Velika Polana","native":null,"lat":"46.57194000","lon":"16.34694000"}]},{"id":4144,"name":"Velike Lašče Municipality","native":null,"cities":[{"id":104306,"name":"Velike Lašče","native":null,"lat":"45.83222000","lon":"14.63639000"}]},{"id":4257,"name":"Veržej Municipality","native":null,"cities":[{"id":104308,"name":"Veržej","native":null,"lat":"46.58361000","lon":"16.16528000"}]},{"id":4300,"name":"Videm Municipality","native":null,"cities":[{"id":104310,"name":"Videm pri Ptuju","native":null,"lat":"46.36861000","lon":"15.90639000"}]},{"id":4196,"name":"Vipava Municipality","native":null,"cities":[{"id":104311,"name":"Vipava","native":null,"lat":"45.84667000","lon":"13.96306000"}]},{"id":4148,"name":"Vitanje Municipality","native":null,"cities":[{"id":104313,"name":"Vitanje","native":null,"lat":"46.38167000","lon":"15.29583000"}]},{"id":4154,"name":"Vodice Municipality","native":null,"cities":[{"id":104317,"name":"Vodice","native":null,"lat":"46.18987000","lon":"14.49492000"}]},{"id":4245,"name":"Vojnik Municipality","native":null,"cities":[{"id":104318,"name":"Vojnik","native":null,"lat":"46.29333000","lon":"15.30333000"}]},{"id":4163,"name":"Vransko Municipality","native":null,"cities":[{"id":104320,"name":"Vransko","native":null,"lat":"46.24389000","lon":"14.95139000"}]},{"id":4262,"name":"Vrhnika Municipality","native":null,"cities":[{"id":104307,"name":"Verd","native":null,"lat":"45.95667000","lon":"14.30583000"},{"id":104321,"name":"Vrhnika","native":null,"lat":"45.96350000","lon":"14.29484000"}]},{"id":4226,"name":"Vuzenica Municipality","native":null,"cities":[{"id":104323,"name":"Vuzenica","native":null,"lat":"46.59639000","lon":"15.16722000"}]},{"id":4269,"name":"Zagorje ob Savi Municipality","native":null,"cities":[{"id":104126,"name":"Izlake","native":null,"lat":"46.15000000","lon":"14.95000000"},{"id":104136,"name":"Kisovec","native":null,"lat":"46.13911000","lon":"14.96295000"},{"id":104325,"name":"Zagorje ob Savi","native":null,"lat":"46.13179000","lon":"14.99694000"}]},{"id":4258,"name":"Žalec Municipality","native":null,"cities":[{"id":104111,"name":"Gotovlje","native":null,"lat":"46.27418000","lon":"15.15186000"},{"id":104344,"name":"Šempeter v Savinj. Dolini","native":null,"lat":"46.25639000","lon":"15.12194000"},{"id":104324,"name":"Zabukovica","native":null,"lat":"46.21408000","lon":"15.15954000"},{"id":104364,"name":"Žalec","native":null,"lat":"46.25151000","lon":"15.16482000"}]},{"id":4182,"name":"Zavrč Municipality","native":null,"cities":[{"id":104327,"name":"Zavrč","native":null,"lat":"46.39167000","lon":"16.04972000"}]},{"id":4256,"name":"Železniki Municipality","native":null,"cities":[{"id":104365,"name":"Železniki","native":null,"lat":"46.22482000","lon":"14.17205000"}]},{"id":4249,"name":"Žetale Municipality","native":null,"cities":[{"id":104366,"name":"Žetale","native":null,"lat":"46.27356000","lon":"15.82658000"}]},{"id":4192,"name":"Žiri Municipality","native":null,"cities":[{"id":104367,"name":"Žiri","native":null,"lat":"46.04222000","lon":"14.10722000"}]},{"id":4276,"name":"Žirovnica Municipality","native":null,"cities":[{"id":104368,"name":"Žirovnica","native":null,"lat":"46.40472000","lon":"14.14000000"}]},{"id":4342,"name":"Zreče Municipality","native":null,"cities":[{"id":104335,"name":"Zreče","native":null,"lat":"46.38222000","lon":"15.37917000"}]},{"id":4307,"name":"Žužemberk Municipality","native":null,"cities":[{"id":104369,"name":"Žužemberk","native":null,"lat":"45.83389000","lon":"14.92917000"}]}]